Workbook

Sheet avance real 
A1: PRESUPUESTO OBRAS CIVILES
A2: Licitación: CONSERVACIÓN ESCUELA JUAN SANDOVAL CARRASCO | E2: Fecha: 03-03-2025 | G2: % Avance | H2: =J152/F152 -> 0.066699314
A3: Ubicación: SANTA ELENA N°385, COQUIMBO | E3: Versión:
A4: Ítem | B4: Descripción | C4: Unidad | D4: Cantidad | E4: P. Unitario ($) | F4: P. Total ($) | G4: Cant avance | H4: unidad | I4: avance % | J4: monto avance
A5: 0 | B5: GENERALIDADES
A6: 1 | B6: OBRAS PREVIAS
A7: 1.1 | B7: Letrero indicativo de la obra | C7: Un | D7: 1 | E7: 1450000 | F7: =D7*E7 -> 1450000 | G7: 1 | H7: unidad | I7: =G7*100%/D7 -> 1 | J7: =F7*I7 -> 1450000
A8: 1.2 | B8: Cierres Provisorios | C8: M. Lineal | D8: 60 | E8: 38500 | F8: =D8*E8 -> 2310000 | G8: 30 | H8: m lineal | I8: =G8*100%/D8 -> 0.5 | J8: =F8*I8 -> 1155000
A9: 1.3 | B9: Intalación de faena
A10: 1.3.1 | B10: Oficina Jefatura | C10: INCLUIDO EN GASTOS GENERALES | G10: INCLUIDO EN GASTOS GENERALES
A11: 1.3.2 | B11: Bodegas | C11: INCLUIDO EN GASTOS GENERALES | G11: INCLUIDO EN GASTOS GENERALES
A12: 1.3.3 | B12: Comedor | C12: INCLUIDO EN GASTOS GENERALES | G12: INCLUIDO EN GASTOS GENERALES
A13: 1.3.4 | B13: Servicios Higienicos | C13: INCLUIDO EN GASTOS GENERALES | G13: INCLUIDO EN GASTOS GENERALES
A14: 1.3.5 | B14: Camarines | C14: INCLUIDO EN GASTOS GENERALES | G14: INCLUIDO EN GASTOS GENERALES
C15: SUBTOTAL
A16: 2 | B16: MEJORAMIENTO
A17: 2.1 | B17: Mejoramiento Complejo de Cubierta
A18: 2.1.1 | B18: Retiro de cubierta existente
A19: 2.1.1.1 | B19: Retiro de cubierta existente zinc | C19: m² | D19: 609.01 | E19: =+P.U!F28 -> 7246 | F19: =ROUND(D19*E19,0) -> 4412886 | G19: 360 | H19: m2 | I19: =G19*100%/D19 -> 0.5911233 | J19: =I19*F19 -> 2608559.7
A20: 2.1.1.2 | B20: Retiro, traslado y dispoción de cubierta de asbesto cemento | C20: m² | D20: 1271.71 | E20: =+P.U!F75 -> 24172 | F20: =ROUND(D20*E20,0) -> 30739774 | I20: =G20*100%/D20 -> 0 | J20: =I20*F20 -> 0
A21: 2.1.2 | B21: Lana de vidrio 91mm R100/213 (Para cubierta PV4) | C21: m² | D21: 1880.72 | E21: =P.U!F114 -> 3885 | F21: =ROUND(D21*E21,0) -> 7306597 | I21: =G21*100%/D21 -> 0 | J21: =I21*F21 -> 0
A22: 2.1.3 | B22: Membrana Hidrofuga Tyvek (Para cubierta PV4) | C22: m² | D22: 1880.72 | E22: =P.U!F159 -> 2611 | F22: =ROUND(D22*E22,0) -> 4910560 | I22: =G22*100%/D22 -> 0 | J22: =I22*F22 -> 0
A23: 2.1.4 | B23: Placa OSB (Para cubierta PV4) | C23: m² | D23: 1880.72 | E23: =P.U!F203 -> 8920 | F23: =ROUND(D23*E23,0) -> 16776022 | G23: 360 | H23: m2 | I23: =G23*100%/D23 -> 0.19141605 | J23: =I23*F23 -> 3211199.9
A24: 2.1.5 | B24: Cubierta PV4 | C24: m² | D24: 1880.72 | E24: =P.U!F248 -> 18515 | F24: =ROUND(D24*E24,0) -> 34821531 | I24: =G24*100%/D24 -> 0 | J24: =I24*F24 -> 0
A25: 2.1.6 | B25: Hojalatería Zincalum liso 0.5mm - CABALLETE | C25: m | D25: 244 | E25: =+P.U!F291 -> 10463 | F25: =ROUND(D25*E25,0) -> 2552972 | G25: =28+15 -> 43 | I25: =G25*100%/D25 -> 0.17622951 | J25: =I25*F25 -> 449909
A26: 2.1.7 | B26: Hojalatería Zincalum liso 0.5mm - CANALETA | C26: m | D26: 175 | E26: =+P.U!F335 -> 27608 | F26: =ROUND(D26*E26,0) -> 4831400 | G26: 28 | I26: =G26*100%/D26 -> 0.16 | J26: =I26*F26 -> 773024
A27: 2.1.8 | B27: Hojalatería Zincalum liso 0.5mm - FORRO Y BAJADAS | C27: m | D27: 102.2 | E27: =+P.U!F379 -> 6368 | F27: =ROUND(D27*E27,0) -> 650810 | G27: =28+28+8+8 -> 72 | I27: =G27*100%/D27 -> 0.70450098 | J27: =I27*F27 -> 458496.28
A28: 2.1.9 | B28: Forro de Aleros y Frontones | C28: m² | D28: 230 | E28: =+P.U!F425 -> 17037 | F28: =ROUND(D28*E28,0) -> 3918510 | I28: =G28*100%/D28 -> 0 | J28: =I28*F28 -> 0
A29: 2.2 | B29: Pavimentos
A30: 2.2.1 | B30: Retiro de revestimiento de piso existente | C30: m² | D30: 1376.95 | E30: =+P.U!F469 -> 3995 | F30: =ROUND(D30*E30,0) -> 5500915 | G30: =(36.3*7)+17.5+55.3 -> 326.9 | H30: m2 | I30: =G30*100%/D30 -> 0.23740877 | J30: =I30*F30 -> 1305965.4
A31: 2.2.2 | B31: Ceramica Blanco mate 60 x 60 cm | C31: m² | D31: 162.96 | E31: =+P.U!F513 -> 25485 | F31: =ROUND(D31*E31,0) -> 4153036 | I31: =G31*100%/D31 -> 0 | J31: =I31*F31 -> 0
A32: 2.2.3 | B32: Porcelanato Artech Gris Mate Inout Antideslizante 23x120 | C32: m² | D32: 1047.99 | E32: =+P.U!F557 -> 37262 | F32: =ROUND(D32*E32,0) -> 39050203 | G32: =(36.3*3)+17.5 -> 126.4 | H32: m2 | I32: =G32*100%/D32 -> 0.12061184 | J32: =I32*F32 -> 4709916.8
A33: 2.2.4 | B33: Guardapolvo para Porcelanato Artech Gris Mate | C33: m | D33: 798.3 | E33: =+P.U!F601 -> 6867 | F33: =ROUND(D33*E33,0) -> 5481926 | G33: =24.5+24.5+24.5+12 -> 85.5 | H33: ml | I33: =G33*100%/D33 -> 0.10710259 | J33: =I33*F33 -> 587128.49
A34: 2.2.5 | B34: Piso vinilico premium excelon raffia stream with dimon 10 | C34: m | D34: 166 | E34: =+P.U!F645 -> 53974 | F34: =ROUND(D34*E34,0) -> 8959684 | I34: =G34*100%/D34 -> 0 | J34: =I34*F34 -> 0
A35: 2.2.6 | B35: Retiro de artefactos existentes | C35: un | D35: 5 | E35: =+P.U!F689 -> 7125 | F35: =ROUND(D35*E35,0) -> 35625 | I35: =G35*100%/D35 -> 0 | J35: =I35*F35 -> 0
A36: 2.2.7 | B36: Pintura Poliuretano Multicancha | C36: m² | D36: 419 | E36: =+P.U!F733 -> 20825 | F36: =ROUND(D36*E36,0) -> 8725675 | I36: =G36*100%/D36 -> 0 | J36: =I36*F36 -> 0
A37: 2.2.8 | B37: Pavimento de seguridad | C37: m² | D37: 138.8 | E37: =+P.U!F777 -> 70625 | F37: =ROUND(D37*E37,0) -> 9802750 | I37: =G37*100%/D37 -> 0 | J37: =I37*F37 -> 0
A38: 2.3 | B38: Terminaciones muros
A39: 2.3.1 | B39: Cerámica Blanco brillante | C39: m² | D39: 377.56 | E39: =+P.U!F821 -> 20560 | F39: =ROUND(D39*E39,0) -> 7762634 | I39: =G39*100%/D39 -> 0 | J39: =I39*F39 -> 0
A40: 2.3.2 | B40: Pintura Esmalte al Agua color por definir | C40: m² | D40: 2312.09 | E40: =+P.U!F865 -> 9445 | F40: =ROUND(D40*E40,0) -> 21837690 | G40: =30*3 -> 90 | H40: m2 | I40: =G40*100%/D40 -> 0.03892582 | J40: =I40*F40 -> 850050
A41: 2.3.3 | B41: Retiro y reinstalación de aparatos eléctricos | C41: un | D41: 15 | E41: =+P.U!F909 -> 7350 | F41: =ROUND(D41*E41,0) -> 110250 | I41: =G41*100%/D41 -> 0 | J41: =I41*F41 -> 0
A42: 2.3.4 | B42: Volcapol | C42: m² | D42: 975.38 | E42: =+P.U!F953 -> 18213 | F42: =ROUND(D42*E42,0) -> 17764596 | I42: =G42*100%/D42 -> 0 | J42: =I42*F42 -> 0
A43: 2.3.5 | B43: Estuco Exterior | C43: m² | D43: 629.1 | E43: =+P.U!F997 -> 17926 | F43: =ROUND(D43*E43,0) -> 11277247 | I43: =G43*100%/D43 -> 0 | J43: =I43*F43 -> 0
A44: 2.3.6 | B44: Pintura Elastomerica Grano Fino | C44: m² | D44: 629.1 | E44: =+P.U!F1041 -> 13208 | F44: =ROUND(D44*E44,0) -> 8309153 | I44: =G44*100%/D44 -> 0 | J44: =I44*F44 -> 0
A45: 2.4 | B45: Terminaciones Cielos
A46: 2.4.1 | B46: Cielo Placa Yeso-Carton ST | C46: m² | D46: 1076.74 | E46: =+P.U!F1089 -> 19992 | F46: =ROUND(D46*E46,0) -> 21526186 | G46: =(36.3+36.3+36.3+55.5)/2 -> 82.2 | H46: m2 | I46: =G46*100%/D46 -> 0.076341549 | J46: =I46*F46 -> 1643342.4
A47: 2.4.2 | B47: Pintura Latex Color Blanco | C47: m² | D47: 508.38 | E47: =+P.U!F1129 -> 10666 | F47: =ROUND(D47*E47,0) -> 5422381 | I47: =G47*100%/D47 -> 0 | J47: =I47*F47 -> 0
A48: 2.4.3 | B48: Cielo panel arquitectonico liso villalba | C48: m² | D48: 553.18 | E48: =+P.U!F1174 -> 25321 | F48: =ROUND(D48*E48,0) -> 14007071 | I48: =G48*100%/D48 -> 0 | J48: =I48*F48 -> 0
A49: 2.6 | B49: Ventanas
A50: 2.6.1 | B50: Retiro de Ventana Existente | C50: m² | D50: 287.3 | E50: =+P.U!F1217 -> 4675 | F50: =ROUND(D50*E50,0) -> 1343128 | G50: 63.36 | H50: m2 | I50: =G50*100%/D50 -> 0.22053603 | J50: =I50*F50 -> 296208.11
A51: 2.6.2 | B51: Estuco de rasgos con mortero preparado | C51: m | D51: 907 | E51: =+P.U!F1261 -> 8743 | F51: =ROUND(D51*E51,0) -> 7929901 | I51: =G51*100%/D51 -> 0 | J51: =I51*F51 -> 0
A52: 2.6.3 | B52: Ventana V1 2,85x1,50 | C52: un | D52: 4 | E52: 635500 | F52: =ROUND(D52*E52,0) -> 2542000 | I52: =G52*100%/D52 -> 0 | J52: =I52*F52 -> 0
A53: 2.6.4 | B53: Ventana V2 1,20x2,60 | C53: un | D53: 1 | E53: 582400 | F53: =ROUND(D53*E53,0) -> 582400 | I53: =G53*100%/D53 -> 0 | J53: =I53*F53 -> 0
A54: 2.6.5 | B54: Ventana V3 2,95x1,60 | C54: un | D54: 1 | E54: 945000 | F54: =ROUND(D54*E54,0) -> 945000 | I54: =G54*100%/D54 -> 0 | J54: =I54*F54 -> 0
A55: 2.6.6 | B55: Ventana V4 1,35x0,7 | C55: un | D55: 2 | E55: 207500 | F55: =ROUND(D55*E55,0) -> 415000 | I55: =G55*100%/D55 -> 0 | J55: =I55*F55 -> 0
A56: 2.6.7 | B56: Ventana V5 2,85x0,50 | C56: un | D56: 2 | E56: 315500 | F56: =ROUND(D56*E56,0) -> 631000 | I56: =G56*100%/D56 -> 0 | J56: =I56*F56 -> 0
A57: 2.6.8 | B57: Ventana V6 1,35x0,50 | C57: un | D57: 3 | E57: 150000 | F57: =ROUND(D57*E57,0) -> 450000 | I57: =G57*100%/D57 -> 0 | J57: =I57*F57 -> 0
A58: 2.6.9 | B58: Ventana V7 0,60x1,50 | C58: un | D58: 16 | E58: 198500 | F58: =ROUND(D58*E58,0) -> 3176000 | I58: =G58*100%/D58 -> 0 | J58: =I58*F58 -> 0
A59: 40215 | B59: Ventana V8 1,60x1,50 | C59: un | D59: 14 | E59: 485000 | F59: =ROUND(D59*E59,0) -> 6790000 | I59: =G59*100%/D59 -> 0 | J59: =I59*F59 -> 0
A60: 40580 | B60: Ventana V9 3,25x1,50 | C60: un | D60: 12 | E60: 985000 | F60: =ROUND(D60*E60,0) -> 11820000 | I60: =G60*100%/D60 -> 0 | J60: =I60*F60 -> 0
A61: 40945 | B61: Ventana V10 4,35x1,50 | C61: un | D61: 12 | E61: 1250000 | F61: =ROUND(D61*E61,0) -> 15000000 | I61: =G61*100%/D61 -> 0 | J61: =I61*F61 -> 0
A62: 41311 | B62: Ventana V11 0,60x1,20 | C62: un | D62: 3 | E62: 165000 | F62: =ROUND(D62*E62,0) -> 495000 | I62: =G62*100%/D62 -> 0 | J62: =I62*F62 -> 0
A63: 41676 | B63: Ventana V12 1,40x0,60 | C63: un | D63: 4 | E63: 185500 | F63: =ROUND(D63*E63,0) -> 742000 | I63: =G63*100%/D63 -> 0 | J63: =I63*F63 -> 0
A64: 42041 | B64: Ventana V13 1,70x0,60 | C64: un | D64: 4 | E64: 225000 | F64: =ROUND(D64*E64,0) -> 900000 | I64: =G64*100%/D64 -> 0 | J64: =I64*F64 -> 0
A65: 42406 | B65: Ventana V14 0,65x1,60 | C65: un | D65: 24 | E65: 235000 | F65: =ROUND(D65*E65,0) -> 5640000 | G65: 24 | H65: unidad | I65: =G65*100%/D65 -> 1 | J65: =I65*F65 -> 5640000
A66: 42772 | B66: Ventana V15 1,60x1,60 | C66: un | D66: 15 | E66: 524000 | F66: =ROUND(D66*E66,0) -> 7860000 | G66: 15 | H66: unidad | I66: =G66*100%/D66 -> 1 | J66: =I66*F66 -> 7860000
A67: 43137 | B67: Ventana V16 5,85x1,50 | C67: un | D67: 2 | E67: 1785000 | F67: =ROUND(D67*E67,0) -> 3570000 | I67: =G67*100%/D67 -> 0 | J67: =I67*F67 -> 0
A68: 43502 | B68: VF1 1,70X0,50 | C68: un | D68: 1 | E68: 145500 | F68: =ROUND(D68*E68,0) -> 145500 | I68: =G68*100%/D68 -> 0 | J68: =I68*F68 -> 0
A69: 43867 | B69: VF2 2,85X0,50 | C69: un | D69: 6 | E69: 240000 | F69: =ROUND(D69*E69,0) -> 1440000 | I69: =G69*100%/D69 -> 0 | J69: =I69*F69 -> 0
A70: 44233 | B70: VF3 1,75X0,50 | C70: un | D70: 1 | E70: 165000 | F70: =ROUND(D70*E70,0) -> 165000 | I70: =G70*100%/D70 -> 0 | J70: =I70*F70 -> 0
A71: 44598 | B71: VF4 3,95X0,50 | C71: un | D71: 1 | E71: 325500 | F71: =ROUND(D71*E71,0) -> 325500 | I71: =G71*100%/D71 -> 0 | J71: =I71*F71 -> 0
A72: 44963 | B72: Malla Mosquitera | C72: m² | D72: 25 | E72: =+P.U!F2187 -> 42536 | F72: =ROUND(D72*E72,0) -> 1063400 | I72: =G72*100%/D72 -> 0 | J72: =I72*F72 -> 0
A73: 45328 | B73: Protecciones | C73: m² | D73: 301.67 | E73: =+P.U!F2231 -> 45950 | F73: =ROUND(D73*E73,0) -> 13861737 | I73: =G73*100%/D73 -> 0 | J73: =I73*F73 -> 0
A74: 2.7 | B74: Puertas
A75: 2.7.1 | B75: Retiro de marco y puerta existentes | C75: un | D75: 67 | E75: =+P.U!F2275 -> 24325 | F75: =ROUND(D75*E75,0) -> 1629775 | G75: 9 | H75: unidad | I75: =G75*100%/D75 -> 0.13432836 | J75: =I75*F75 -> 218925
A76: 2.7.2 | B76: Estuco de rasgos con mortero preparado | C76: m | D76: 271.05 | E76: =+P.U!F2319 -> 13093 | F76: =ROUND(D76*E76,0) -> 3548858 | I76: =G76*100%/D76 -> 0 | J76: =I76*F76 -> 0
A77: 2.7.3 | B77: Puerta P1 Ancho 0,80M | C77: un | D77: 7 | E77: =+P.U!F2363 -> 134775 | F77: =ROUND(D77*E77,0) -> 943425 | I77: =G77*100%/D77 -> 0 | J77: =I77*F77 -> 0
A78: 2.7.4 | B78: Puerta P2 Ancho 0,75M | C78: un | D78: 10 | E78: =+P.U!F2409 -> 139775 | F78: =ROUND(D78*E78,0) -> 1397750 | I78: =G78*100%/D78 -> 0 | J78: =I78*F78 -> 0
A79: 2.7.5 | B79: Puerta P3 Ancho 0,70M | C79: un | D79: 8 | E79: =+P.U!F2453 -> 157875 | F79: =ROUND(D79*E79,0) -> 1263000 | I79: =G79*100%/D79 -> 0 | J79: =I79*F79 -> 0
A80: 2.7.6 | B80: Puerta P4 Ancho 1,3M | C80: un | D80: 21 | E80: =+P.U!F2497 -> 584950 | F80: =ROUND(D80*E80,0) -> 12283950 | G80: 0 | I80: =G80*100%/D80 -> 0 | J80: =I80*F80 -> 0
A81: 2.7.7 | B81: Puerta P5 Ancho 0,95M | C81: un | D81: 13 | E81: =+P.U!F2541 -> 381575 | F81: =ROUND(D81*E81,0) -> 4960475 | I81: =G81*100%/D81 -> 0 | J81: =I81*F81 -> 0
A82: 2.7.8 | B82: Puerta P6 Ancho 0,95M | C82: un | D82: 4 | E82: =+P.U!F2585 -> 165875 | F82: =ROUND(D82*E82,0) -> 663500 | I82: =G82*100%/D82 -> 0 | J82: =I82*F82 -> 0
A83: 2.7.9 | B83: Puerta P7 Ancho 0,90M | C83: un | D83: 4 | E83: =+P.U!F2629 -> 157875 | F83: =ROUND(D83*E83,0) -> 631500 | I83: =G83*100%/D83 -> 0 | J83: =I83*F83 -> 0
A84: 40216 | B84: Quincallería | J84: =I84*F84 -> 0
A85: 2.7.10.1 | B85: Manilla libre paso | C85: un | D85: 67 | E85: =+P.U!F2671 -> 26941 | F85: =ROUND(D85*E85,0) -> 1805047 | I85: =G85*100%/D85 -> 0 | J85: =I85*F85 -> 0
A86: 2.7.10.2 | B86: Cerradura | C86: un | D86: 67 | E86: =+P.U!F2715 -> 46983 | F86: =ROUND(D86*E86,0) -> 3147861 | I86: =G86*100%/D86 -> 0 | J86: =I86*F86 -> 0
A87: 2.7.10.3 | B87: Tope de puerta | C87: un | D87: 67 | E87: =+P.U!F2759 -> 15857 | F87: =ROUND(D87*E87,0) -> 1062419 | I87: =G87*100%/D87 -> 0 | J87: =I87*F87 -> 0
A88: 2.8 | B88: Artefactos Sanitarios
A89: 2.8.1 | B89: Barra de Sujeción abatible | C89: un | D89: 1 | E89: =+P.U!F2803 -> 111725 | F89: =ROUND(D89*E89,0) -> 111725 | I89: =G89*100%/D89 -> 0 | J89: =I89*F89 -> 0
A90: 2.8.2 | B90: Barra de Sujeción fija recta | C90: un | D90: 1 | E90: =+P.U!F2847 -> 41725 | F90: =ROUND(D90*E90,0) -> 41725 | I90: =G90*100%/D90 -> 0 | J90: =I90*F90 -> 0
A91: 2.8.3 | B91: Dispensador de Jabon | C91: un | D91: 16 | E91: =+P.U!F2891 -> 25375 | F91: =ROUND(D91*E91,0) -> 406000 | I91: =G91*100%/D91 -> 0 | J91: =I91*F91 -> 0
A92: 2.8.4 | B92: Dispensador de toallas de Papel | C92: un | D92: 12 | E92: =+P.U!F2935 -> 34375 | F92: =ROUND(D92*E92,0) -> 412500 | I92: =G92*100%/D92 -> 0 | J92: =I92*F92 -> 0
A93: 2.8.5 | B93: División de baño | C93: Un | D93: 13 | E93: =+P.U!F2979 -> 268000 | F93: =ROUND(D93*E93,0) -> 3484000 | I93: =G93*100%/D93 -> 0 | J93: =I93*F93 -> 0
A94: 2.8.6 | B94: Ducha fija | C94: un | D94: 11 | E94: =+P.U!F3023 -> 35200 | F94: =ROUND(D94*E94,0) -> 387200 | I94: =G94*100%/D94 -> 0 | J94: =I94*F94 -> 0
A95: 2.8.7 | B95: Espejo con Bisel 60 x 90cm | C95: un | D95: 13 | E95: =+P.U!F3067 -> 45200 | F95: =ROUND(D95*E95,0) -> 587600 | I95: =G95*100%/D95 -> 0 | J95: =I95*F95 -> 0
A96: 2.8.8 | B96: Lavamanos pedestal | C96: un | D96: 8 | E96: =+P.U!F3111 -> 92250 | F96: =ROUND(D96*E96,0) -> 738000 | I96: =G96*100%/D96 -> 0 | J96: =I96*F96 -> 0
A97: 2.8.9 | B97: Lavamanos pedestal Niños | C97: un | D97: 7 | E97: =+P.U!F3155 -> 95250 | F97: =ROUND(D97*E97,0) -> 666750 | I97: =G97*100%/D97 -> 0 | J97: =I97*F97 -> 0
A98: 40217 | B98: Porta rollo Jumbo | C98: un | D98: 18 | E98: =+P.U!F3199 -> 27375 | F98: =ROUND(D98*E98,0) -> 492750 | I98: =G98*100%/D98 -> 0 | J98: =I98*F98 -> 0
A99: 40582 | B99: Sanitario Discapacitados | C99: un | D99: 1 | E99: =+P.U!F3243 -> 194000 | F99: =ROUND(D99*E99,0) -> 194000 | I99: =G99*100%/D99 -> 0 | J99: =I99*F99 -> 0
A100: 40947 | B100: Sanitario | C100: un | D100: 17 | E100: =+P.U!F3287 -> 164000 | F100: =ROUND(D100*E100,0) -> 2788000 | I100: =G100*100%/D100 -> 0 | J100: =I100*F100 -> 0
...

Sheet avance proyectado 20%
A1: PRESUPUESTO OBRAS CIVILES
A2: Licitación: CONSERVACIÓN ESCUELA JUAN SANDOVAL CARRASCO | E2: Fecha: 17-03-2025 | G2: % Avance | H2: =J152/F152 -> 0.20395051
A3: Ubicación: SANTA ELENA N°385, COQUIMBO | E3: Versión:
A4: Ítem | B4: Descripción | C4: Unidad | D4: Cantidad | E4: P. Unitario ($) | F4: P. Total ($) | G4: Cant avance | H4: unidad | I4: avance % | J4: monto avance
A5: 0 | B5: GENERALIDADES
A6: 1 | B6: OBRAS PREVIAS
A7: 1.1 | B7: Letrero indicativo de la obra | C7: Un | D7: 1 | E7: 1450000 | F7: =D7*E7 -> 1450000 | G7: 1 | H7: unidad | I7: =G7*100%/D7 -> 1 | J7: =F7*I7 -> 1450000
A8: 1.2 | B8: Cierres Provisorios | C8: Ml | D8: 60 | E8: 38500 | F8: =D8*E8 -> 2310000 | G8: 30 | H8: m lineal | I8: =G8*100%/D8 -> 0.5 | J8: =F8*I8 -> 1155000
A9: 1.3 | B9: Intalación de faena
A10: 1.3.1 | B10: Oficina Jefatura | C10: INCLUIDO EN GASTOS GENERALES | G10: INCLUIDO EN GASTOS GENERALES
A11: 1.3.2 | B11: Bodegas | C11: INCLUIDO EN GASTOS GENERALES | G11: INCLUIDO EN GASTOS GENERALES
A12: 1.3.3 | B12: Comedor | C12: INCLUIDO EN GASTOS GENERALES | G12: INCLUIDO EN GASTOS GENERALES
A13: 1.3.4 | B13: Servicios Higienicos | C13: INCLUIDO EN GASTOS GENERALES | G13: INCLUIDO EN GASTOS GENERALES
A14: 1.3.5 | B14: Camarines | C14: INCLUIDO EN GASTOS GENERALES | G14: INCLUIDO EN GASTOS GENERALES
C15: SUBTOTAL
A16: 2 | B16: MEJORAMIENTO
A17: 2.1 | B17: Mejoramiento Complejo de Cubierta
A18: 2.1.1 | B18: Retiro de cubierta existente
A19: 2.1.1.1 | B19: Retiro de cubierta existente zinc | C19: m² | D19: 609.01 | E19: =+P.U!F28 -> 7246 | F19: =ROUND(D19*E19,0) -> 4412886 | G19: 360 | H19: m2 | I19: =G19*100%/D19 -> 0.5911233 | J19: =I19*F19 -> 2608559.7
A20: 2.1.1.2 | B20: Retiro, traslado y dispoción de cubierta de asbesto cemento | C20: m² | D20: 1271.71 | E20: =+P.U!F75 -> 24172 | F20: =ROUND(D20*E20,0) -> 30739774 | I20: =G20*100%/D20 -> 0 | J20: =I20*F20 -> 0
A21: 2.1.2 | B21: Lana de vidrio 91mm R100/213 (Para cubierta PV4) | C21: m² | D21: 1880.72 | E21: =P.U!F114 -> 3885 | F21: =ROUND(D21*E21,0) -> 7306597 | G21: 360 | I21: =G21*100%/D21 -> 0.19141605 | J21: =I21*F21 -> 1398600
A22: 2.1.3 | B22: Membrana Hidrofuga Tyvek (Para cubierta PV4) | C22: m² | D22: 1880.72 | E22: =P.U!F159 -> 2611 | F22: =ROUND(D22*E22,0) -> 4910560 | G22: 360 | I22: =G22*100%/D22 -> 0.19141605 | J22: =I22*F22 -> 939960.02
A23: 2.1.4 | B23: Placa OSB (Para cubierta PV4) | C23: m² | D23: 1880.72 | E23: =P.U!F203 -> 8920 | F23: =ROUND(D23*E23,0) -> 16776022 | G23: 360 | H23: m2 | I23: =G23*100%/D23 -> 0.19141605 | J23: =I23*F23 -> 3211199.9
A24: 2.1.5 | B24: Cubierta PV4 | C24: m² | D24: 1880.72 | E24: =P.U!F248 -> 18515 | F24: =ROUND(D24*E24,0) -> 34821531 | G24: 360 | I24: =G24*100%/D24 -> 0.19141605 | J24: =I24*F24 -> 6665400
A25: 2.1.6 | B25: Hojalatería Zincalum liso 0.5mm - CABALLETE | C25: m | D25: 244 | E25: =+P.U!F291 -> 10463 | F25: =ROUND(D25*E25,0) -> 2552972 | G25: =28+15+13 -> 56 | I25: =G25*100%/D25 -> 0.2295082 | J25: =I25*F25 -> 585928
A26: 2.1.7 | B26: Hojalatería Zincalum liso 0.5mm - CANALETA | C26: m | D26: 175 | E26: =+P.U!F335 -> 27608 | F26: =ROUND(D26*E26,0) -> 4831400 | G26: =28+28 -> 56 | I26: =G26*100%/D26 -> 0.32 | J26: =I26*F26 -> 1546048
A27: 2.1.8 | B27: Hojalatería Zincalum liso 0.5mm - FORRO Y BAJADAS | C27: m | D27: 102.2 | E27: =+P.U!F379 -> 6368 | F27: =ROUND(D27*E27,0) -> 650810 | G27: 102.2 | I27: =G27*100%/D27 -> 1 | J27: =I27*F27 -> 650810
A28: 2.1.9 | B28: Forro de Aleros y Frontones | C28: m² | D28: 230 | E28: =+P.U!F425 -> 17037 | F28: =ROUND(D28*E28,0) -> 3918510 | I28: =G28*100%/D28 -> 0 | J28: =I28*F28 -> 0
A29: 2.2 | B29: Pavimentos
A30: 2.2.1 | B30: Retiro de revestimiento de piso existente | C30: m² | D30: 1376.95 | E30: =+P.U!F469 -> 3995 | F30: =ROUND(D30*E30,0) -> 5500915 | G30: =(36.3*7)+55.5+17.5 -> 327.1 | H30: m2 | I30: =G30*100%/D30 -> 0.23755401 | J30: =I30*F30 -> 1306764.4
A31: 2.2.2 | B31: Ceramica Blanco mate 60 x 60 cm | C31: m² | D31: 162.96 | E31: =+P.U!F513 -> 25485 | F31: =ROUND(D31*E31,0) -> 4153036 | I31: =G31*100%/D31 -> 0 | J31: =I31*F31 -> 0
A32: 2.2.3 | B32: Porcelanato Artech Gris Mate Inout Antideslizante 23x120 | C32: m² | D32: 1047.99 | E32: =+P.U!F557 -> 37262 | F32: =ROUND(D32*E32,0) -> 39050203 | G32: 327.1 | H32: m2 | I32: =G32*100%/D32 -> 0.3121213 | J32: =I32*F32 -> 12188400
A33: 2.2.4 | B33: Guardapolvo para Porcelanato Artech Gris Mate | C33: m | D33: 798.3 | E33: =+P.U!F601 -> 6867 | F33: =ROUND(D33*E33,0) -> 5481926 | G33: =(24.5*8) -> 196 | H33: ml | I33: =G33*100%/D33 -> 0.24552173 | J33: =I33*F33 -> 1345932
A34: 2.2.5 | B34: Piso vinilico premium excelon raffia stream with dimon 10 | C34: m | D34: 166 | E34: =+P.U!F645 -> 53974 | F34: =ROUND(D34*E34,0) -> 8959684 | G34: 166 | I34: =G34*100%/D34 -> 1 | J34: =I34*F34 -> 8959684
A35: 2.2.6 | B35: Retiro de artefactos existentes | C35: un | D35: 5 | E35: =+P.U!F689 -> 7125 | F35: =ROUND(D35*E35,0) -> 35625 | I35: =G35*100%/D35 -> 0 | J35: =I35*F35 -> 0
A36: 2.2.7 | B36: Pintura Poliuretano Multicancha | C36: m² | D36: 419 | E36: =+P.U!F733 -> 20825 | F36: =ROUND(D36*E36,0) -> 8725675 | I36: =G36*100%/D36 -> 0 | J36: =I36*F36 -> 0
A37: 2.2.8 | B37: Pavimento de seguridad | C37: m² | D37: 138.8 | E37: =+P.U!F777 -> 70625 | F37: =ROUND(D37*E37,0) -> 9802750 | I37: =G37*100%/D37 -> 0 | J37: =I37*F37 -> 0
A38: 2.3 | B38: Terminaciones muros
A39: 2.3.1 | B39: Cerámica Blanco brillante | C39: m² | D39: 377.56 | E39: =+P.U!F821 -> 20560 | F39: =ROUND(D39*E39,0) -> 7762634 | I39: =G39*100%/D39 -> 0 | J39: =I39*F39 -> 0
A40: 2.3.2 | B40: Pintura Esmalte al Agua color por definir | C40: m² | D40: 2312.09 | E40: =+P.U!F865 -> 9445 | F40: =ROUND(D40*E40,0) -> 21837690 | G40: 1205.72 | H40: m2 | I40: =G40*100%/D40 -> 0.52148489 | J40: =I40*F40 -> 11388025
A41: 2.3.3 | B41: Retiro y reinstalación de aparatos eléctricos | C41: un | D41: 15 | E41: =+P.U!F909 -> 7350 | F41: =ROUND(D41*E41,0) -> 110250 | I41: =G41*100%/D41 -> 0 | J41: =I41*F41 -> 0
A42: 2.3.4 | B42: Volcapol | C42: m² | D42: 975.38 | E42: =+P.U!F953 -> 18213 | F42: =ROUND(D42*E42,0) -> 17764596 | I42: =G42*100%/D42 -> 0 | J42: =I42*F42 -> 0
A43: 2.3.5 | B43: Estuco Exterior | C43: m² | D43: 629.1 | E43: =+P.U!F997 -> 17926 | F43: =ROUND(D43*E43,0) -> 11277247 | I43: =G43*100%/D43 -> 0 | J43: =I43*F43 -> 0
A44: 2.3.6 | B44: Pintura Elastomerica Grano Fino | C44: m² | D44: 629.1 | E44: =+P.U!F1041 -> 13208 | F44: =ROUND(D44*E44,0) -> 8309153 | I44: =G44*100%/D44 -> 0 | J44: =I44*F44 -> 0
A45: 2.4 | B45: Terminaciones Cielos
A46: 2.4.1 | B46: Cielo Placa Yeso-Carton ST | C46: m² | D46: 1076.74 | E46: =+P.U!F1089 -> 19992 | F46: =ROUND(D46*E46,0) -> 21526186 | G46: 175 | H46: m2 | I46: =G46*100%/D46 -> 0.16252763 | J46: =I46*F46 -> 3498600
A47: 2.4.2 | B47: Pintura Latex Color Blanco | C47: m² | D47: 508.38 | E47: =+P.U!F1129 -> 10666 | F47: =ROUND(D47*E47,0) -> 5422381 | G47: 479 | I47: =G47*100%/D47 -> 0.94220858 | J47: =I47*F47 -> 5109013.9
A48: 2.4.3 | B48: Cielo panel arquitectonico liso villalba | C48: m² | D48: 553.18 | E48: =+P.U!F1174 -> 25321 | F48: =ROUND(D48*E48,0) -> 14007071 | G48: 180 | I48: =G48*100%/D48 -> 0.32539137 | J48: =I48*F48 -> 4557780.1
A49: 2.6 | B49: Ventanas
A50: 2.6.1 | B50: Retiro de Ventana Existente | C50: m² | D50: 287.3 | E50: =+P.U!F1217 -> 4675 | F50: =ROUND(D50*E50,0) -> 1343128 | G50: 63.36 | H50: m2 | I50: =G50*100%/D50 -> 0.22053603 | J50: =I50*F50 -> 296208.11
A51: 2.6.2 | B51: Estuco de rasgos con mortero preparado | C51: m | D51: 907 | E51: =+P.U!F1261 -> 8743 | F51: =ROUND(D51*E51,0) -> 7929901 | G51: =(((1.6+1.6+1.6+1.6)*15))+(((0.65*0.65+1.6+1.6)*24)) -> 182.94 | H51: m | I51: =G51*100%/D51 -> 0.20169791 | J51: =I51*F51 -> 1599444.4
A52: 2.6.3 | B52: Ventana V1 2,85x1,50 | C52: un | D52: 4 | E52: 635500 | F52: =ROUND(D52*E52,0) -> 2542000 | I52: =G52*100%/D52 -> 0 | J52: =I52*F52 -> 0
A53: 2.6.4 | B53: Ventana V2 1,20x2,60 | C53: un | D53: 1 | E53: 582400 | F53: =ROUND(D53*E53,0) -> 582400 | I53: =G53*100%/D53 -> 0 | J53: =I53*F53 -> 0
A54: 2.6.5 | B54: Ventana V3 2,95x1,60 | C54: un | D54: 1 | E54: 945000 | F54: =ROUND(D54*E54,0) -> 945000 | I54: =G54*100%/D54 -> 0 | J54: =I54*F54 -> 0
A55: 2.6.6 | B55: Ventana V4 1,35x0,7 | C55: un | D55: 2 | E55: 207500 | F55: =ROUND(D55*E55,0) -> 415000 | I55: =G55*100%/D55 -> 0 | J55: =I55*F55 -> 0
A56: 2.6.7 | B56: Ventana V5 2,85x0,50 | C56: un | D56: 2 | E56: 315500 | F56: =ROUND(D56*E56,0) -> 631000 | I56: =G56*100%/D56 -> 0 | J56: =I56*F56 -> 0
A57: 2.6.8 | B57: Ventana V6 1,35x0,50 | C57: un | D57: 3 | E57: 150000 | F57: =ROUND(D57*E57,0) -> 450000 | I57: =G57*100%/D57 -> 0 | J57: =I57*F57 -> 0
A58: 2.6.9 | B58: Ventana V7 0,60x1,50 | C58: un | D58: 16 | E58: 198500 | F58: =ROUND(D58*E58,0) -> 3176000 | I58: =G58*100%/D58 -> 0 | J58: =I58*F58 -> 0
A59: 40215 | B59: Ventana V8 1,60x1,50 | C59: un | D59: 14 | E59: 485000 | F59: =ROUND(D59*E59,0) -> 6790000 | I59: =G59*100%/D59 -> 0 | J59: =I59*F59 -> 0
A60: 40580 | B60: Ventana V9 3,25x1,50 | C60: un | D60: 12 | E60: 985000 | F60: =ROUND(D60*E60,0) -> 11820000 | I60: =G60*100%/D60 -> 0 | J60: =I60*F60 -> 0
A61: 40945 | B61: Ventana V10 4,35x1,50 | C61: un | D61: 12 | E61: 1250000 | F61: =ROUND(D61*E61,0) -> 15000000 | I61: =G61*100%/D61 -> 0 | J61: =I61*F61 -> 0
A62: 41311 | B62: Ventana V11 0,60x1,20 | C62: un | D62: 3 | E62: 165000 | F62: =ROUND(D62*E62,0) -> 495000 | I62: =G62*100%/D62 -> 0 | J62: =I62*F62 -> 0
A63: 41676 | B63: Ventana V12 1,40x0,60 | C63: un | D63: 4 | E63: 185500 | F63: =ROUND(D63*E63,0) -> 742000 | I63: =G63*100%/D63 -> 0 | J63: =I63*F63 -> 0
A64: 42041 | B64: Ventana V13 1,70x0,60 | C64: un | D64: 4 | E64: 225000 | F64: =ROUND(D64*E64,0) -> 900000 | I64: =G64*100%/D64 -> 0 | J64: =I64*F64 -> 0
A65: 42406 | B65: Ventana V14 0,65x1,60 | C65: un | D65: 24 | E65: 235000 | F65: =ROUND(D65*E65,0) -> 5640000 | G65: 24 | H65: unidad | I65: =G65*100%/D65 -> 1 | J65: =I65*F65 -> 5640000
A66: 42772 | B66: Ventana V15 1,60x1,60 | C66: un | D66: 15 | E66: 524000 | F66: =ROUND(D66*E66,0) -> 7860000 | G66: 15 | H66: unidad | I66: =G66*100%/D66 -> 1 | J66: =I66*F66 -> 7860000
A67: 43137 | B67: Ventana V16 5,85x1,50 | C67: un | D67: 2 | E67: 1785000 | F67: =ROUND(D67*E67,0) -> 3570000 | I67: =G67*100%/D67 -> 0 | J67: =I67*F67 -> 0
A68: 43502 | B68: VF1 1,70X0,50 | C68: un | D68: 1 | E68: 145500 | F68: =ROUND(D68*E68,0) -> 145500 | I68: =G68*100%/D68 -> 0 | J68: =I68*F68 -> 0
A69: 43867 | B69: VF2 2,85X0,50 | C69: un | D69: 6 | E69: 240000 | F69: =ROUND(D69*E69,0) -> 1440000 | I69: =G69*100%/D69 -> 0 | J69: =I69*F69 -> 0
A70: 44233 | B70: VF3 1,75X0,50 | C70: un | D70: 1 | E70: 165000 | F70: =ROUND(D70*E70,0) -> 165000 | I70: =G70*100%/D70 -> 0 | J70: =I70*F70 -> 0
A71: 44598 | B71: VF4 3,95X0,50 | C71: un | D71: 1 | E71: 325500 | F71: =ROUND(D71*E71,0) -> 325500 | I71: =G71*100%/D71 -> 0 | J71: =I71*F71 -> 0
A72: 44963 | B72: Malla Mosquitera | C72: m² | D72: 25 | E72: =+P.U!F2187 -> 42536 | F72: =ROUND(D72*E72,0) -> 1063400 | I72: =G72*100%/D72 -> 0 | J72: =I72*F72 -> 0
A73: 45328 | B73: Protecciones | C73: m² | D73: 301.67 | E73: =+P.U!F2231 -> 45950 | F73: =ROUND(D73*E73,0) -> 13861737 | G73: 64 | I73: =G73*100%/D73 -> 0.21215235 | J73: =I73*F73 -> 2940800.1
A74: 2.7 | B74: Puertas
A75: 2.7.1 | B75: Retiro de marco y puerta existentes | C75: un | D75: 67 | E75: =+P.U!F2275 -> 24325 | F75: =ROUND(D75*E75,0) -> 1629775 | G75: 9 | H75: unidad | I75: =G75*100%/D75 -> 0.13432836 | J75: =I75*F75 -> 218925
A76: 2.7.2 | B76: Estuco de rasgos con mortero preparado | C76: m | D76: 271.05 | E76: =+P.U!F2319 -> 13093 | F76: =ROUND(D76*E76,0) -> 3548858 | G76: =((1.3+1.3+3+3)*9) -> 77.4 | I76: =G76*100%/D76 -> 0.28555617 | J76: =I76*F76 -> 1013398.3
A77: 2.7.3 | B77: Puerta P1 Ancho 0,80M | C77: un | D77: 7 | E77: =+P.U!F2363 -> 134775 | F77: =ROUND(D77*E77,0) -> 943425 | I77: =G77*100%/D77 -> 0 | J77: =I77*F77 -> 0
A78: 2.7.4 | B78: Puerta P2 Ancho 0,75M | C78: un | D78: 10 | E78: =+P.U!F2409 -> 139775 | F78: =ROUND(D78*E78,0) -> 1397750 | I78: =G78*100%/D78 -> 0 | J78: =I78*F78 -> 0
A79: 2.7.5 | B79: Puerta P3 Ancho 0,70M | C79: un | D79: 8 | E79: =+P.U!F2453 -> 157875 | F79: =ROUND(D79*E79,0) -> 1263000 | I79: =G79*100%/D79 -> 0 | J79: =I79*F79 -> 0
A80: 2.7.6 | B80: Puerta P4 Ancho 1,3M | C80: un | D80: 21 | E80: =+P.U!F2497 -> 584950 | F80: =ROUND(D80*E80,0) -> 12283950 | G80: 9 | I80: =G80*100%/D80 -> 0.42857143 | J80: =I80*F80 -> 5264550
A81: 2.7.7 | B81: Puerta P5 Ancho 0,95M | C81: un | D81: 13 | E81: =+P.U!F2541 -> 381575 | F81: =ROUND(D81*E81,0) -> 4960475 | I81: =G81*100%/D81 -> 0 | J81: =I81*F81 -> 0
A82: 2.7.8 | B82: Puerta P6 Ancho 0,95M | C82: un | D82: 4 | E82: =+P.U!F2585 -> 165875 | F82: =ROUND(D82*E82,0) -> 663500 | I82: =G82*100%/D82 -> 0 | J82: =I82*F82 -> 0
A83: 2.7.9 | B83: Puerta P7 Ancho 0,90M | C83: un | D83: 4 | E83: =+P.U!F2629 -> 157875 | F83: =ROUND(D83*E83,0) -> 631500 | I83: =G83*100%/D83 -> 0 | J83: =I83*F83 -> 0
A84: 40216 | B84: Quincallería | J84: =I84*F84 -> 0
A85: 2.7.10.1 | B85: Manilla libre paso | C85: un | D85: 67 | E85: =+P.U!F2671 -> 26941 | F85: =ROUND(D85*E85,0) -> 1805047 | G85: 9 | I85: =G85*100%/D85 -> 0.13432836 | J85: =I85*F85 -> 242469
A86: 2.7.10.2 | B86: Cerradura | C86: un | D86: 67 | E86: =+P.U!F2715 -> 46983 | F86: =ROUND(D86*E86,0) -> 3147861 | G86: 9 | I86: =G86*100%/D86 -> 0.13432836 | J86: =I86*F86 -> 422847
A87: 2.7.10.3 | B87: Tope de puerta | C87: un | D87: 67 | E87: =+P.U!F2759 -> 15857 | F87: =ROUND(D87*E87,0) -> 1062419 | G87: 9 | I87: =G87*100%/D87 -> 0.13432836 | J87: =I87*F87 -> 142713
A88: 2.8 | B88: Artefactos Sanitarios
A89: 2.8.1 | B89: Barra de Sujeción abatible | C89: un | D89: 1 | E89: =+P.U!F2803 -> 111725 | F89: =ROUND(D89*E89,0) -> 111725 | I89: =G89*100%/D89 -> 0 | J89: =I89*F89 -> 0
A90: 2.8.2 | B90: Barra de Sujeción fija recta | C90: un | D90: 1 | E90: =+P.U!F2847 -> 41725 | F90: =ROUND(D90*E90,0) -> 41725 | I90: =G90*100%/D90 -> 0 | J90: =I90*F90 -> 0
A91: 2.8.3 | B91: Dispensador de Jabon | C91: un | D91: 16 | E91: =+P.U!F2891 -> 25375 | F91: =ROUND(D91*E91,0) -> 406000 | I91: =G91*100%/D91 -> 0 | J91: =I91*F91 -> 0
A92: 2.8.4 | B92: Dispensador de toallas de Papel | C92: un | D92: 12 | E92: =+P.U!F2935 -> 34375 | F92: =ROUND(D92*E92,0) -> 412500 | I92: =G92*100%/D92 -> 0 | J92: =I92*F92 -> 0
A93: 2.8.5 | B93: División de baño | C93: Un | D93: 13 | E93: =+P.U!F2979 -> 268000 | F93: =ROUND(D93*E93,0) -> 3484000 | I93: =G93*100%/D93 -> 0 | J93: =I93*F93 -> 0
A94: 2.8.6 | B94: Ducha fija | C94: un | D94: 11 | E94: =+P.U!F3023 -> 35200 | F94: =ROUND(D94*E94,0) -> 387200 | I94: =G94*100%/D94 -> 0 | J94: =I94*F94 -> 0
A95: 2.8.7 | B95: Espejo con Bisel 60 x 90cm | C95: un | D95: 13 | E95: =+P.U!F3067 -> 45200 | F95: =ROUND(D95*E95,0) -> 587600 | I95: =G95*100%/D95 -> 0 | J95: =I95*F95 -> 0
A96: 2.8.8 | B96: Lavamanos pedestal | C96: un | D96: 8 | E96: =+P.U!F3111 -> 92250 | F96: =ROUND(D96*E96,0) -> 738000 | I96: =G96*100%/D96 -> 0 | J96: =I96*F96 -> 0
A97: 2.8.9 | B97: Lavamanos pedestal Niños | C97: un | D97: 7 | E97: =+P.U!F3155 -> 95250 | F97: =ROUND(D97*E97,0) -> 666750 | I97: =G97*100%/D97 -> 0 | J97: =I97*F97 -> 0
A98: 40217 | B98: Porta rollo Jumbo | C98: un | D98: 18 | E98: =+P.U!F3199 -> 27375 | F98: =ROUND(D98*E98,0) -> 492750 | I98: =G98*100%/D98 -> 0 | J98: =I98*F98 -> 0
A99: 40582 | B99: Sanitario Discapacitados | C99: un | D99: 1 | E99: =+P.U!F3243 -> 194000 | F99: =ROUND(D99*E99,0) -> 194000 | I99: =G99*100%/D99 -> 0 | J99: =I99*F99 -> 0
A100: 40947 | B100: Sanitario | C100: un | D100: 17 | E100: =+P.U!F3287 -> 164000 | F100: =ROUND(D100*E100,0) -> 2788000 | I100: =G100*100%/D100 -> 0 | J100: =I100*F100 -> 0
...

Sheet P.U
A1: Rendimiento (Un/jornada): | B1: 56 | C1: (edita este valor) | E1: Parámetros (editar):
A2: Unidad de pago: | B2: m² | E2: Gastos Generales | F2: 0.15
E3: Utilidad | F3: 0.2
B4: 2.1.1.1 Retiro cubierta existen | E4: iva | F4: 0.19
A5: MATERIALES
A6: # | B6: Descripción / Material | C6: Unidad | D6: Cantidad | E6: $ Unitario | F6: Subtotal
A7: 1 | B7: Film Polietileno 200 mic (protección) | C7: m² | D7: =ROUND(1/$B$1,2) -> 0.02 | E7: 388 | F7: =ROUND(IFERROR(D7*E7,0),0) -> 8
A8: 2 | B8: Sacos polipropileno 50 kg | C8: un | D8: =ROUND(1/$B$1,2) -> 0.02 | E8: 4613 | F8: =ROUND(IFERROR(D8*E8,0),0) -> 92
A9: 3 | B9: Consumibles (cintas/discos) | C9: gl | D9: =ROUND(1/$B$1,2) -> 0.02 | E9: 4832 | F9: =ROUND(IFERROR(D9*E9,0),0) -> 97
E10: TOTAL | F10: =ROUND(SUM(F6:F9),0) -> 197
A12: MANO DE OBRA (Rendimiento por jornada)
A13: # | B13: Descripción / Material | C13: Unidad | D13: Cantidad | E13: $ Unitario | F13: Subtotal
A14: 1 | B14: Maestro techumbre | C14: día | D14: 0.03 | E14: 65000 | F14: =ROUND(IFERROR(D14*E14,0),0) -> 1950
A15: 2 | B15: Ayudante | C15: día | D15: 0.03 | E15: 50000 | F15: =ROUND(IFERROR(D15*E15,0),0) -> 1500
E16: TOTAL | F16: =SUM(F14:F15) -> 3450
E17: Leyes sociales 50% | F17: =F16*0.5 -> 1725
E18: TOTAL MO | F18: =F16+F17 -> 5175
A20: MAQUINARIA Y HERRAMIENTAS (prorrateo por unidad)
A21: # | B21: Descripción / Material | C21: Unidad | D21: Cantidad | E21: $ Unitario | F21: Subtotal
A22: 1 | B22: Andamio (prorrateo) | C22: día | D22: 0.03 | E22: 7000 | F22: =ROUND(IFERROR(D22*E22,0),0) -> 210
A23: 2 | B23: Camión 3/4 (apoyo) | C23: día | D23: 0.03 | E23: 55454 | F23: =ROUND(IFERROR(D23*E23,0),0) -> 1664
E24: TOTAL | F24: =SUM(F22:F23) -> 1874
A26: RESUMEN
B27: Descripción / Material | C27: Unidad | D27: Cantidad | E27: $ Unitario | F27: Subtotal
E28: Costo Directo | F28: =F10+F18+F24 -> 7246
E29: Gastos Generales | F29: =ROUND(F28*F2,0) -> 1087
E30: Utilidad | F30: =ROUND(F28*F3,0) -> 1449
E31: Sub-Total Neto | F31: =F28+F29+F30 -> 9782
E32: IVA 19% | F32: =ROUND(F30*0.19,0) -> 275
D33: (m²) | E33: PRECIO UNITARIO | F33: =F31+F32 -> 10057
A45: Rendimiento (Un/jornada): | B45: 40 | C45: (edita este valor) | E45: Parámetros (editar):
A46: Unidad de pago: | B46: m² | E46: Gastos Generales | F46: 0.15
E47: Utilidad | F47: 0.2
B48: 2.1.1.2 Retiro, traslado y disp | E48: Utilidad | F48: 0.19
A49: MATERIALES
A50: # | B50: Descripción / Material | C50: Unidad | D50: Cantidad | E50: $ Unitario | F50: Subtotal
A51: 1 | B51: Polietileno 200 mic (encapsulado) | C51: m² | D51: 0.3 | E51: 388 | F51: =ROUND(IFERROR(D51*E51,0),0) -> 116
A52: 2 | B52: Bolsas residuo peligroso rotuladas | C52: un | D52: 0.25 | E52: 4613 | F52: =ROUND(IFERROR(D52*E52,0),0) -> 1153
A53: 3 | B53: Sellante PU (sellos/bolsas) | C53: cart | D53: 0.04 | E53: 4832 | F53: =ROUND(IFERROR(D53*E53,0),0) -> 193
A54: 4 | B54: Buzos desechables tipo Tyvek 4520 | C54: un | D54: 0.4 | E54: 1891 | F54: =ROUND(IFERROR(D54*E54,0),0) -> 756
A55: 5 | B55: Filtros P100 3M 2097 (par) | C55: par | D55: 0.2 | E55: 11504 | F55: =ROUND(IFERROR(D55*E55,0),0) -> 2301
A56: 6 | B56: Transporte + Disposición final (gestor RESPEL DS148) | C56: m3 | D56: 1 | E56: 10500 | F56: =ROUND(IFERROR(D56*E56,0),0) -> 10500
E57: TOTAL | F57: =SUM(F51:F56) -> 15019
A59: MANO DE OBRA (Rendimiento por jornada)
A60: # | B60: Descripción / Material | C60: Unidad | D60: Cantidad | E60: $ Unitario | F60: Subtotal
A61: 1 | B61: Maestro acreditado (MCA) | C61: día | D61: 0.04 | E61: 65000 | F61: =ROUND(IFERROR(D61*E61,0),0) -> 2600
A62: 2 | B62: Ayudante | C62: día | D62: 0.04 | E62: 50000 | F62: =ROUND(IFERROR(D62*E62,0),0) -> 2000
E63: TOTAL | F63: =SUM(F61:F62) -> 4600
E64: Leyes sociales 50% | F64: =F63*0.5 -> 2300
E65: TOTAL MO | F65: =F63+F64 -> 6900
A67: MAQUINARIA Y HERRAMIENTAS (prorrateo por unidad)
A68: # | B68: Descripción / Material | C68: Unidad | D68: Cantidad | E68: $ Unitario | F68: Subtotal
A69: 1 | B69: Andamio (línea de vida/arnés) | C69: día | D69: =ROUND(0.25/B45,2) -> 0.01 | E69: 3500 | F69: =ROUND(IFERROR(D69*E69,0),0) -> 35
A70: 2 | B70: Camión 3/4 (apoyo) | C70: día | D70: 0.04 | E70: 55454 | F70: =ROUND(IFERROR(D70*E70,0),0) -> 2218
E71: TOTAL | F71: =SUM(F69:F70) -> 2253
A73: RESUMEN
B74: Descripción / Material | C74: Unidad | D74: Cantidad | E74: $ Unitario | F74: Subtotal
E75: Costo Directo | F75: =F57+F65+F71 -> 24172
E76: Gastos Generales | F76: =ROUND(F75*F46,0) -> 3626
E77: Utilidad | F77: =ROUND(F75*F47,0) -> 4834
E78: Sub-Total Neto | F78: =F75+F76+F77 -> 32632
E79: IVA 19% | F79: =ROUND(F78*F48,0) -> 6200
D80: (m²) | E80: PRECIO UNITARIO | F80: =F78+F79 -> 38832
A89: Rendimiento (Un/jornada): | B89: 70 | C89: (edita este valor) | E89: Parámetros (editar):
A90: Unidad de pago: | B90: m² | E90: Gastos Generales | F90: 0.15
E91: Utilidad | F91: 0.2
B92: 2.1.2 Lana de vidrio 91mm R100- | E92: iva | F92: 0.19
A93: MATERIALES
A94: # | B94: Descripción / Material | C94: Unidad | D94: Cantidad | E94: $ Unitario | F94: Subtotal
A95: 1 | B95: Lana de vidrio 90 mm | C95: m² | D95: 1 | E95: 2000 | F95: =ROUND(IFERROR(D95*E95,0),0) -> 2000
A96: 2 | B96: Grapa inoxidable / fijación | C96: un | D96: 10 | E96: 16 | F96: =ROUND(IFERROR(D96*E96,0),0) -> 160
E97: TOTAL | F97: =SUM(F95:F96) -> 2160
A99: MANO DE OBRA (Rendimiento por jornada)
A100: # | B100: Descripción / Material | C100: Unidad | D100: Cantidad | E100: $ Unitario | F100: Subtotal
A101: 1 | B101: Instalador | C101: día | D101: 0.01 | E101: 65000 | F101: =ROUND(IFERROR(D101*E101,0),0) -> 650
A102: 2 | B102: Ayudante | C102: día | D102: 0.01 | E102: 50000 | F102: =ROUND(IFERROR(D102*E102,0),0) -> 500
E103: TOTAL | F103: =SUM(F101:F102) -> 1150
E104: Leyes sociales 50% | F104: =ROUND(F103*0.5,0) -> 575
E105: TOTAL MO | F105: =F103+F104 -> 1725
A107: MAQUINARIA Y HERRAMIENTAS (prorrateo por unidad)
A108: # | B108: Descripción / Material | C108: Unidad | D108: Cantidad | E108: $ Unitario | F108: Subtotal
A109: 1 | B109: Andamio (apoyo) | C109: día | D109: =ROUND(0.3/B89,2) -> 0 | E109: 3500 | F109: =ROUND(IFERROR(D109*E109,0),0) -> 0
E110: TOTAL | F110: =SUM(F109) -> 0
A112: RESUMEN
B113: Descripción / Material | C113: Unidad | D113: Cantidad | E113: $ Unitario | F113: Subtotal
E114: Costo Directo | F114: =ROUND(F97+F105+F110,0) -> 3885
E115: Gastos Generales | F115: =ROUND(F114*F90,0) -> 583
E116: Utilidad | F116: =ROUND(F114*F91,0) -> 777
E117: Sub-Total Neto | F117: =ROUND(F114+F115+F116,0) -> 5245
E118: IVA 19% | F118: =ROUND(F117*F92,0) -> 997
D119: (m²) | E119: PRECIO UNITARIO | F119: =F117+F118 -> 6242
A133: Rendimiento (Un/jornada): | B133: 100 | C133: (edita este valor) | E133: Parámetros (editar):
A134: Unidad de pago: | B134: m² | E134: Gastos Generales | F134: 0.15
E135: Utilidad | F135: 0.2
B136: 2.1.3 Membrana Hidrofuga Tyvek | E136: iva | F136: 0.19
A137: MATERIALES
A138: # | B138: Descripción / Material | C138: Unidad | D138: Cantidad | E138: $ Unitario | F138: Subtotal
A139: 1 | B139: Membrana hidrófuga (rollo 75 m²) | C139: m² | D139: 1 | E139: 900 | F139: =ROUND(IFERROR(D139*E139,0),0) -> 900
A140: 2 | B140: Grapa inoxidable | C140: un | D140: 8 | E140: 16 | F140: =ROUND(IFERROR(D140*E140,0),0) -> 128
A141: 3 | B141: Sellante PU (solapes) | C141: cart | D141: 0.01 | E141: 4832 | F141: =ROUND(IFERROR(D141*E141,0),0) -> 48
...

Sheet Anexo 4
A1: Anexo N°4
A3: ANÁLISIS DE PRECIOS UNITARIOS
A5: NOMBRE DE LA OBRA: SERVICIO DE OBRAS DE CONSERVACIÓN EN ESCUELA JUAN SANDOVAL CARRASCO DEL SERVICIO LOCAL DE EDUCACIÓN PÚBLICA PUERTO CORDILLERA.
A6: ID
A7: CONTRATISTA: CONSTRUCTORA RCR SPA
A9: PARTIDA | B9: =+P.U!B224 -> Cubierta PV4 | C9: ITEM : | D9: UNIDAD | F9: PRECIO
C10: =+P.U!A224 -> 2.1.5 | D10: =+P.U!B222 -> m² | F10: UNITARIO
A11: NOMBRE | F11: =+P.U!F248 -> 18515
A13: MATERIALES (A)
A14: Nº | B14: ITEM | C14: UNIDAD | D14: CANTIDAD | E14: PRECIO | F14: VALOR
E15: UNITARIO | F15: TOTAL
A16: =+P.U!A227 -> 1 | B16: =+P.U!B227 -> Plancha PV4 0,5 mm c/ anticondensante | C16: =+P.U!C227 -> m² | D16: =+P.U!D227 -> 1.05 | E16: =+P.U!E227 -> 10250 | F16: =+P.U!F227 -> 10763
A17: =+P.U!A228 -> 2 | B17: =+P.U!B228 -> Tornillo c/ arandela neopreno | C17: =+P.U!C228 -> un | D17: =+P.U!D228 -> 8 | E17: =+P.U!E228 -> 80 | F17: =+P.U!F228 -> 640
A18: =+P.U!A229 -> 3 | B18: =+P.U!B229 -> Sellante PU remates | C18: =+P.U!C229 -> cart | D18: =+P.U!D229 -> 0.02 | E18: =+P.U!E229 -> 4832 | F18: =+P.U!F229 -> 97
E21: TOTAL | F21: =+P.U!F230 -> 11500
A24: MANO DE OBRA (B)
A25: Nº | B25: ITEM | C25: UNIDAD | D25: CANTIDAD | E25: PRECIO | F25: VALOR
E26: UNITARIO | F26: TOTAL
A27: =+P.U!A234 -> 1 | B27: =+P.U!B234 -> Techador | C27: =+P.U!C234 -> día | D27: =+P.U!D234 -> 0.04 | E27: =+P.U!E234 -> 65000 | F27: =+P.U!F234 -> 2600
A28: =+P.U!A235 -> 2 | B28: =+P.U!B235 -> Ayudante | C28: =+P.U!C235 -> día | D28: =+P.U!D235 -> 0.04 | E28: =+P.U!E235 -> 50000 | F28: =+P.U!F235 -> 2000
E31: SUBTOTAL M.O | F31: =+P.U!F236 -> 4600
B32: LEYES SOCIALES | C32: % | D32: =+P.U!F237 -> 2300
E33: TOTAL MO | F33: =+P.U!F238 -> 6900
A36: EQUIPOS Y HERRAMIENTAS (C)
A37: Nº | B37: ITEM | C37: UNIDAD | D37: CANTIDAD | E37: PRECIO | F37: VALOR
E38: UNITARIO | F38: TOTAL
A39: =+P.U!A242 -> 1 | B39: =+P.U!B242 -> Atornillador | C39: =+P.U!C242 -> día | D39: =+P.U!D242 -> 0.01 | E39: =+P.U!E242 -> 8000 | F39: =+P.U!F242 -> 80
A40: =+P.U!A243 -> 2 | B40: =+P.U!B243 -> Andamio (apoyo) | C40: =+P.U!C243 -> día | D40: =+P.U!D243 -> 0.01 | E40: =+P.U!E243 -> 3500 | F40: =+P.U!F243 -> 35
E43: TOTAL | F43: =+P.U!F244 -> 115
B47: ____________________________________
B48: ROGER CARMONA / 12,441,221-8
B49: REPRESENTANTE LEGAL
B50: CONSTRUCTORA RCR SPA
A53: Anexo N°4
A55: ANÁLISIS DE PRECIOS UNITARIOS
A57: NOMBRE DE LA OBRA: SERVICIO DE OBRAS DE CONSERVACIÓN EN ESCUELA JUAN SANDOVAL CARRASCO DEL SERVICIO LOCAL DE EDUCACIÓN PÚBLICA PUERTO CORDILLERA.
A58: ID
A59: CONTRATISTA: CONSTRUCTORA RCR SPA
A61: PARTIDA | B61: Porcel. Artech gris mate inout antides 23x120 | C61: ITEM : | D61: UNIDAD | F61: PRECIO
C62: =+P.U!A532 -> 2.2.3 | D62: =+P.U!B530 -> m² | F62: UNITARIO
A63: NOMBRE | F63: =+P.U!F557 -> 37262
A65: MATERIALES (A)
A66: Nº | B66: ITEM | C66: UNIDAD | D66: CANTIDAD | E66: PRECIO | F66: VALOR
E67: UNITARIO | F67: TOTAL
A68: =+P.U!A535 -> 1 | B68: =+P.U!B535 -> Porcelanato Artech Gris Mate Inout 23x120 | C68: =+P.U!C535 -> m2 | D68: =+P.U!D535 -> 1.05 | E68: =+P.U!E535 -> 19500 | F68: =+P.U!F535 -> 20475
A69: =+P.U!A536 -> 2 | B69: =+P.U!B536 -> Adhesivo DA 25 kg (6 kg/m²) | C69: =+P.U!C536 -> kg | D69: =+P.U!D536 -> 6 | E69: =+P.U!E536 -> 312 | F69: =+P.U!F536 -> 1872
A70: =+P.U!A537 -> 3 | B70: =+P.U!B537 -> Fragüe 1 kg (0,35 kg/m²) | C70: =+P.U!C537 -> kg | D70: =+P.U!D537 -> 0.35 | E70: =+P.U!E537 -> 1592 | F70: =+P.U!F537 -> 557
A71: =+P.U!A538 -> 4 | B71: =+P.U!B538 -> Niveladores/Clips (12 un/m²) | C71: =+P.U!C538 -> un | D71: =+P.U!D538 -> 12 | E71: =+P.U!E538 -> 34 | F71: =+P.U!F538 -> 408
E73: TOTAL | F73: =+P.U!F539 -> 23312
A76: MANO DE OBRA (B)
A77: Nº | B77: ITEM | C77: UNIDAD | D77: CANTIDAD | E77: PRECIO | F77: VALOR
E78: UNITARIO | F78: TOTAL
A79: =+P.U!A543 -> 1 | B79: =+P.U!B543 -> Maestro | C79: =+P.U!C543 -> día | D79: =+P.U!D543 -> 0.1 | E79: =+P.U!E543 -> 65000 | F79: =+P.U!F543 -> 6500
A80: =+P.U!A544 -> 2 | B80: =+P.U!B544 -> Ayudante | C80: =+P.U!C544 -> día | D80: =+P.U!D544 -> 0.05 | E80: =+P.U!E544 -> 50000 | F80: =+P.U!F544 -> 2500
E83: SUBTOTAL M.O | F83: =+P.U!F545 -> 9000
B84: LEYES SOCIALES | C84: % | D84: =+P.U!F546 -> 4500
F85: =+P.U!F547 -> 13500
A88: EQUIPOS Y HERRAMIENTAS (C)
A89: Nº | B89: ITEM | C89: UNIDAD | D89: CANTIDAD | E89: PRECIO | F89: VALOR
E90: UNITARIO | F90: TOTAL
A91: =+P.U!A551 -> 1 | B91: =+P.U!B551 -> Desagaste herramientas | C91: =+P.U!C551 -> día | D91: =+P.U!D551 -> 0.01 | E91: =+P.U!E551 -> 45000 | F91: =+P.U!F551 -> 450
E95: TOTAL | F95: =+P.U!F553 -> 450
B99: ____________________________________
B100: ROGER CARMONA / 12,441,221-8
B101: REPRESENTANTE LEGAL
B102: CONSTRUCTORA RCR SPA
A105: Anexo N°4
A107: ANÁLISIS DE PRECIOS UNITARIOS
A109: NOMBRE DE LA OBRA: SERVICIO DE OBRAS DE CONSERVACIÓN EN ESCUELA JUAN SANDOVAL CARRASCO DEL SERVICIO LOCAL DE EDUCACIÓN PÚBLICA PUERTO CORDILLERA.
A110: ID
A111: CONTRATISTA: CONSTRUCTORA RCR SPA
A114: PARTIDA | B114: Cielo placa yeso carton ST | C114: ITEM : | D114: UNIDAD | F114: PRECIO
C115: =+P.U!A1060 -> 2.4.1 | D115: =+P.U!B1058 -> m² | F115: UNITARIO
A116: NOMBRE | F116: =+P.U!F1089 -> 19992
A118: MATERIALES (A)
A119: Nº | B119: ITEM | C119: UNIDAD | D119: CANTIDAD | E119: PRECIO | F119: VALOR
E120: UNITARIO | F120: TOTAL
A121: =IF(+P.U!A1063=0," ",P.U!A1063) -> 1 | B121: =IF(+P.U!B1063=0," ",P.U!B1063) -> Placa yeso-cartón ST 10 mm | C121: =IF(+P.U!C1063=0," ",P.U!C1063) -> m² | D121: =IF(+P.U!D1063=0," ",P.U!D1063) -> 1 | E121: =IF(+P.U!E1063=0," ",P.U!E1063) -> 2550 | F121: =IF(+P.U!F1063=0," ",P.U!F1063) -> 2550
A122: =IF(+P.U!A1064=0," ",P.U!A1064) -> 2 | B122: =IF(+P.U!B1064=0," ",P.U!B1064) -> Perfil Omega 0,5 mm (2,5 ml/m²) | C122: =IF(+P.U!C1064=0," ",P.U!C1064) -> ml | D122: =IF(+P.U!D1064=0," ",P.U!D1064) -> 2.5 | E122: =IF(+P.U!E1064=0," ",P.U!E1064) -> 529 | F122: =IF(+P.U!F1064=0," ",P.U!F1064) -> 1323
A123: =IF(+P.U!A1065=0," ",P.U!A1065) -> 3 | B123: =IF(+P.U!B1065=0," ",P.U!B1065) -> Canal perimetral 20x25 (0,20 ml/m²) | C123: =IF(+P.U!C1065=0," ",P.U!C1065) -> ml | D123: =IF(+P.U!D1065=0," ",P.U!D1065) -> 0.2 | E123: =IF(+P.U!E1065=0," ",P.U!E1065) -> 417 | F123: =IF(+P.U!F1065=0," ",P.U!F1065) -> 83
A124: =IF(+P.U!A1066=0," ",P.U!A1066) -> 4 | B124: =IF(+P.U!B1066=0," ",P.U!B1066) -> Tornillo yeso-cartón 1-1/4" (20 u/m²) | C124: =IF(+P.U!C1066=0," ",P.U!C1066) -> un | D124: =IF(+P.U!D1066=0," ",P.U!D1066) -> 20 | E124: =IF(+P.U!E1066=0," ",P.U!E1066) -> 8 | F124: =IF(+P.U!F1066=0," ",P.U!F1066) -> 160
A125: =IF(+P.U!A1067=0," ",P.U!A1067) -> 5 | B125: =IF(+P.U!B1067=0," ",P.U!B1067) -> Cinta papel 50 mm (1,0 ml/m²) | C125: =IF(+P.U!C1067=0," ",P.U!C1067) -> ml | D125: =IF(+P.U!D1067=0," ",P.U!D1067) -> 1 | E125: =IF(+P.U!E1067=0," ",P.U!E1067) -> 53 | F125: =IF(+P.U!F1067=0," ",P.U!F1067) -> 53
A126: =IF(+P.U!A1068=0," ",P.U!A1068) -> 6 | B126: =IF(+P.U!B1068=0," ",P.U!B1068) -> Masilla juntas 25 kg (0,35 kg/m²) | C126: =IF(+P.U!C1068=0," ",P.U!C1068) -> kg | D126: =IF(+P.U!D1068=0," ",P.U!D1068) -> 0.35 | E126: =IF(+P.U!E1068=0," ",P.U!E1068) -> 924 | F126: =IF(+P.U!F1068=0," ",P.U!F1068) -> 323
A127: =IF(+P.U!A1069=0," ",P.U!A1069) -> 7 | B127: =IF(+P.U!B1069=0," ",P.U!B1069) -> Consumibles y anclajes (prorrateo) | C127: =IF(+P.U!C1069=0," ",P.U!C1069) -> gl | D127: =IF(+P.U!D1069=0," ",P.U!D1069) -> 1 | E127: =IF(+P.U!E1069=0," ",P.U!E1069) -> 800 | F127: =IF(+P.U!F1069=0," ",P.U!F1069) -> 800
A128: =IF(+P.U!A1070=0," ",P.U!A1070)
A129: =IF(+P.U!A1071=0," ",P.U!A1071) | B129: =IF(+P.U!B1070=0," ",P.U!B1070) | C129: =IF(+P.U!C1070=0," ",P.U!C1070) | D129: =IF(+P.U!D1070=0," ",P.U!D1070) | E129: =IF(+P.U!E1070=0," ",P.U!E1070) | F129: =IF(+P.U!F1070=0," ",P.U!F1070)
E130: TOTAL | F130: =+P.U!F1071 -> 5292
A133: MANO DE OBRA (B)
A134: Nº | B134: ITEM | C134: UNIDAD | D134: CANTIDAD | E134: PRECIO | F134: VALOR
E135: UNITARIO | F135: TOTAL
A136: =IF(P.U!A1075=0," ",P.U!A1075) -> 1 | B136: =IF(P.U!B1075=0," ",P.U!B1075) -> Maestro | C136: =IF(P.U!C1075=0," ",P.U!C1075) -> día | D136: =IF(P.U!D1075=0," ",P.U!D1075) -> 0.08 | E136: =IF(P.U!E1075=0," ",P.U!E1075) -> 65000 | F136: =IF(P.U!F1075=0," ",P.U!F1075) -> 5200
A137: =IF(P.U!A1076=0," ",P.U!A1076) -> 2 | B137: =IF(P.U!B1076=0," ",P.U!B1076) -> Ayudante | C137: =IF(P.U!C1076=0," ",P.U!C1076) -> día | D137: =IF(P.U!D1076=0," ",P.U!D1076) -> 0.08 | E137: =IF(P.U!E1076=0," ",P.U!E1076) -> 50000 | F137: =IF(P.U!F1076=0," ",P.U!F1076) -> 4000
A138: =IF(P.U!A1077=0," ",P.U!A1077) | B138: =IF(P.U!B1077=0," ",P.U!B1077) | C138: =IF(P.U!C1077=0," ",P.U!C1077) | D138: =IF(P.U!D1077=0," ",P.U!D1077)
E140: SUBTOTAL M.O | F140: =+P.U!F1077 -> 9200
B141: LEYES SOCIALES | C141: % | F141: =+P.U!F1078 -> 4600
F142: =+P.U!F1079 -> 13800
A145: EQUIPOS Y HERRAMIENTAS (C)
A146: Nº | B146: ITEM | C146: UNIDAD | D146: CANTIDAD | E146: PRECIO | F146: VALOR
E147: UNITARIO | F147: TOTAL
A148: =IF(+P.U!A1083=0," ",P.U!A1083) -> 1 | B148: =IF(+P.U!B1083=0," ",P.U!B1083) -> Desagaste herramientas | C148: =IF(+P.U!C1083=0," ",P.U!C1083) -> día | D148: =IF(+P.U!D1083=0," ",P.U!D1083) -> 0.02 | E148: =IF(+P.U!E1083=0," ",P.U!E1083) -> 45000 | F148: =IF(+P.U!F1083=0," ",P.U!F1083) -> 900
...
